cosmctl/__init__.py
cosmctl/main.py
cosmctl/modules/__init__.py
cosmctl/modules/argsparser.py
cosmctl/modules/commands.py
cosmctl/modules/scanner.py
cosmctl/utils/Parser.py
cosmctl/utils/__init__.py
cosmctl/utils/loader.py
cosmctl/utils/scanner.py
cosmctl-0.1.10.dist-info/METADATA
cosmctl-0.1.10.dist-info/WHEEL
cosmctl-0.1.10.dist-info/entry_points.txt
cosmctl-0.1.10.dist-info/top_level.txt
cosmctl-0.1.10.dist-info/RECORD
